envsmith/__init__.py
envsmith/__main__.py
envsmith/_types.py
envsmith/cli.py
envsmith/core.py
envsmith/schema_loader.py
envsmith/secrets.py
envsmith/validation.py
envsmith/integrations/__init__.py
envsmith/integrations/django.py
envsmith/integrations/fastapi.py
envsmith-0.1.0.dist-info/licenses/LICENSE
envsmith-0.1.0.dist-info/METADATA
envsmith-0.1.0.dist-info/WHEEL
envsmith-0.1.0.dist-info/entry_points.txt
envsmith-0.1.0.dist-info/top_level.txt
envsmith-0.1.0.dist-info/RECORD
