Metadata-Version: 2.4
Name: envsmith
Version: 0.1.0
Summary: Modern, schema-first environment variable loader and manager for Python.
Author-email: Peyman Tahmasebi <peymantahmasebi10@gmail.com>
License: MIT License
Project-URL: Homepage, https://github.com/PeymanSohi/envsmith
Project-URL: Documentation, https://github.com/PeymanSohi/envsmith#readme
Project-URL: Source, https://github.com/PeymanSohi/envsmith
Project-URL: Changelog, https://github.com/PeymanSohi/envsmith/blob/main/CHANGELOG.md
Keywords: environment,dotenv,validation,schema,fastapi,django
Classifier: Development Status :: 4 - Beta
Classifier: Intended Audience :: Developers
Classifier: License :: OSI Approved :: MIT License
Classifier: Programming Language :: Python :: 3
Classifier: Programming Language :: Python :: 3 :: Only
Classifier: Programming Language :: Python :: 3.8
Classifier: Programming Language :: Python :: 3.9
Classifier: Programming Language :: Python :: 3.10
Classifier: Programming Language :: Python :: 3.11
Classifier: Programming Language :: Python :: 3.12
Classifier: Topic :: Software Development :: Libraries
Classifier: Topic :: Utilities
Requires-Python: >=3.8
License-File: LICENSE
Requires-Dist: pyyaml>=6.0
Requires-Dist: python-dotenv>=1.0.0
Requires-Dist: pydantic>=2.0.0
Provides-Extra: fastapi
Requires-Dist: fastapi>=0.100.0; extra == "fastapi"
Provides-Extra: django
Requires-Dist: django>=4.0.0; extra == "django"
Dynamic: license-file
